{
  "race_no": 80,
  "updated_at": "2026-05-23T23:55:12.450Z",
  "results": [
    {
      "lane": 2,
      "rank": 1,
      "times": {
        "500m": {
          "time_ms": 116470,
          "formatted": "1:56.47"
        },
        "1000m": {
          "time_ms": 235300,
          "formatted": "3:55.30"
        }
      },
      "finish": {
        "time_ms": 235300,
        "formatted": "3:55.30"
      },
      "split": "(1:58.83)",
      "tie_group": "",
      "photo_flag": false,
      "note": "",
      "status": "finish"
    },
    {
      "lane": 5,
      "rank": 2,
      "times": {
        "500m": {
          "time_ms": 118100,
          "formatted": "1:58.10"
        },
        "1000m": {
          "time_ms": 239390,
          "formatted": "3:59.39"
        }
      },
      "finish": {
        "time_ms": 239390,
        "formatted": "3:59.39"
      },
      "split": "(2:01.29)",
      "tie_group": "",
      "photo_flag": false,
      "note": "",
      "status": "finish"
    },
    {
      "lane": 3,
      "rank": 3,
      "times": {
        "500m": {
          "time_ms": 131310,
          "formatted": "2:11.31"
        },
        "1000m": {
          "time_ms": 257980,
          "formatted": "4:17.98"
        }
      },
      "finish": {
        "time_ms": 257980,
        "formatted": "4:17.98"
      },
      "split": "(2:06.67)",
      "tie_group": "",
      "photo_flag": false,
      "note": "",
      "status": "finish"
    },
    {
      "lane": 4,
      "rank": 4,
      "times": {
        "500m": {
          "time_ms": 132170,
          "formatted": "2:12.17"
        },
        "1000m": {
          "time_ms": 264470,
          "formatted": "4:24.47"
        }
      },
      "finish": {
        "time_ms": 264470,
        "formatted": "4:24.47"
      },
      "split": "(2:12.30)",
      "tie_group": "",
      "photo_flag": false,
      "note": "",
      "status": "finish"
    }
  ]
}